Workbook

Sheet Read Me
A1: SHIJO.AI
A2: AI Visibility Tracking — Cost Breakdown, Option A vs Option B
A3: Prepared for review — July 19, 2026
A5: Purpose
A6: Models what AI-visibility/GEO tracking (the feature scoped in docs/product/2026-07-19-AI-Visibility-Tracking-Scoping.docx) would actually cost per scan and per month, for both build options, stacked on top of the AI cost this project already carries per plan (the same worst-case-per-generation methodology already used and trusted in the Enterprise fair-use fix, pricing review doc section 8).
A8: How to use this
A9: Blue cells are editable inputs — vendor pricing (Sheet 2), token/volume assumptions (Sheet 2), and assumed scans/month per plan (Sheet 4, currently placeholders since quota-per-plan is an open decision, not yet set). Everything else is a live formula and recalculates automatically when you change a blue cell.
A11: What is NOT in this model
A12: Real measured token usage (nothing has been built yet, so input/output token counts are modeled estimates, not logged data — clearly marked in Sheet 2). Vendor account minimums/contract terms beyond list pricing. Engineering time/cost to build either option (this is API/inference cost only, not build cost — see the scoping doc for the engineering-effort read).
A14: Sheets
A15: 2. Vendor Pricing & Assumptions — sourced per-unit costs for every vendor involved, plus the token-count assumptions the model uses.
A16: 3. Cost Per Scan — Option A vs B — what one AI-visibility check costs under each option, broken into its component API calls.
A17: 4. Monthly Cost vs Plan Revenue — stacks the new feature cost on top of the AI cost SHIJO already carries per plan, at adjustable monthly scan volumes, compared against each plan's price.

Sheet Vendor Pricing & Assumptions
A1: Vendor Pricing (sourced, July 2026)
A3: Vendor / Model | B3: Input $ / 1M tok | C3: Output $ / 1M tok | D3: Per-request fee | E3: Source
A4: Anthropic Claude Sonnet 4.6 (already in use — 9/12 tools) | B4: 3 | C4: 15 | D4: 0 | E4: finout.io / cloudzero.com Anthropic pricing summaries, July 2026 — matches the $3/$15 figure already used in this project's own Enterprise fair-use calc.
A5: Anthropic Claude Haiku 4.5 (already in use — 3/12 tools + all Free-plan gens) | B5: 1 | C5: 5 | D5: 0 | E5: Same sources as above — matches the $1/$5 figure already used in this project.
A6: OpenAI GPT-4o (Option B — ChatGPT leg) | B6: 2.5 | C6: 10 | D6: 0 | E6: cloudzero.com / pecollective.com OpenAI pricing summaries, July 2026.
A7: OpenAI GPT-4o-mini (Option B — cheaper ChatGPT leg alternative) | B7: 0.15 | C7: 0.6 | D7: 0 | E7: Same sources — far cheaper but a materially different (weaker) model than what most ChatGPT users actually see by default.
A8: Perplexity Sonar Pro (Option B — Perplexity leg) | B8: 3 | C8: 15 | D8: 0.0095 | E8: docs.perplexity.ai / cloudzero.com, July 2026 — token cost plus a $5-$14 per 1,000-request fee (mid-point $9.50/1,000 = $0.0095/request modeled here); confirm exact fee tier against docs.perplexity.ai before committing budget.
A9: Perplexity Sonar (base, Option B — cheaper Perplexity leg alternative) | B9: 1 | C9: 1 | D9: 0.0095 | E9: Same source — cheaper token rate, same modeled request fee.
A10: DataForSEO SERP API w/ AI Overview, Live priority (Option B — Google AI Overview leg) | B10: 0 | C10: 0 | D10: 0.004 | E10: dataforseo.com/pricing/serp — $4.00 per 1,000 AI-Overview-enabled Live queries ($0.004/query), modeled as a flat per-request fee since there is no token pricing for this endpoint.
A11: SerpApi w/ AI Overview included (Option B — Google AI Overview leg, alternative vendor) | B11: 0 | C11: 0 | D11: 0.005 | E11: serpapi.com/pricing — $5.00 per 1,000 queries, AI Overview included at no separate surcharge; DataForSEO is the cheaper of the two at list price.
A13: Token / Volume Assumptions — MODELED, not measured (nothing is built yet)
A14: These estimate a structured visibility-check prompt/response (query + brand + short JSON verdict), which is shorter than the full-length copy the 12 existing content tools generate. Re-check against real logged token counts once any version of this ships.
A16: Assumption | B16: Value (tokens)
A17: Input tokens per scan (query + brand + context, same across all engines) | B17: 500
A18: Output tokens per scan — structured verdict (mentioned/position/sentiment/reasoning) | B18: 350

Sheet Cost Per Scan (A vs B)
A1: Cost Per Scan — Option A vs Option B
A3: One "scan" = one AI-visibility check for one brand + one query.
A5: OPTION A — Claude-only simulation
A6: Component call | B6: Input $/1M | C6: Output $/1M | D6: Cost per scan | E6: Note
A7: Claude Sonnet 4.6 — single call, own simulated assessment | B7: ='Vendor Pricing & Assumptions'!B4 -> 3 | C7: ='Vendor Pricing & Assumptions'!C4 -> 15 | D7: =('Vendor Pricing & Assumptions'!$B$17*'Vendor Pricing & Assumptions'!B4+'Vendor Pricing & Assumptions'!$B$18*'Vendor Pricing & Assumptions'!C4)/1000000+'Vendor Pricing & Assumptions'!D4 -> 0.00675 | E7: Higher quality, matches the model already used on 9/12 existing tools.
A8: Claude Haiku 4.5 — single call, own simulated assessment (cheaper alt) | B8: ='Vendor Pricing & Assumptions'!B5 -> 1 | C8: ='Vendor Pricing & Assumptions'!C5 -> 5 | D8: =('Vendor Pricing & Assumptions'!$B$17*'Vendor Pricing & Assumptions'!B5+'Vendor Pricing & Assumptions'!$B$18*'Vendor Pricing & Assumptions'!C5)/1000000+'Vendor Pricing & Assumptions'!D5 -> 0.00225 | E8: Cheaper, matches the model already used for all Free-plan generations. Likely weaker simulated judgment.
A10: Option A total per scan (Sonnet) | D10: =D7 -> 0.00675
A11: Option A total per scan (Haiku) | D11: =D8 -> 0.00225
A13: OPTION B — real multi-engine tracking (ChatGPT + Perplexity + Google AI Overview)
A14: Component call | B14: Input $/1M | C14: Output $/1M | D14: Cost per scan | E14: Note
A15: OpenAI GPT-4o — real ChatGPT-leg query | B15: ='Vendor Pricing & Assumptions'!B6 -> 2.5 | C15: ='Vendor Pricing & Assumptions'!C6 -> 10 | D15: =('Vendor Pricing & Assumptions'!$B$17*'Vendor Pricing & Assumptions'!B6+'Vendor Pricing & Assumptions'!$B$18*'Vendor Pricing & Assumptions'!C6)/1000000+'Vendor Pricing & Assumptions'!D6 -> 0.00475 | E15: Requires a new OpenAI API key/account — does not exist in this project today.
A16: Perplexity Sonar Pro — real Perplexity-leg query | B16: ='Vendor Pricing & Assumptions'!B8 -> 3 | C16: ='Vendor Pricing & Assumptions'!C8 -> 15 | D16: =('Vendor Pricing & Assumptions'!$B$17*'Vendor Pricing & Assumptions'!B8+'Vendor Pricing & Assumptions'!$B$18*'Vendor Pricing & Assumptions'!C8)/1000000+'Vendor Pricing & Assumptions'!D8 -> 0.01625 | E16: Requires a new Perplexity API key/account — does not exist in this project today. Includes modeled per-request fee.
A17: DataForSEO SERP API (AI Overview, Live) — real Google AI Overview capture | B17: ='Vendor Pricing & Assumptions'!B10 -> 0 | C17: ='Vendor Pricing & Assumptions'!C10 -> 0 | D17: =('Vendor Pricing & Assumptions'!$B$17*'Vendor Pricing & Assumptions'!B10+'Vendor Pricing & Assumptions'!$B$18*'Vendor Pricing & Assumptions'!C10)/1000000+'Vendor Pricing & Assumptions'!D10 -> 0.004 | E17: Requires a new DataForSEO (or SerpApi) account — does not exist in this project today. No public Google AI Overview API exists; this is a third-party SERP-capture workaround.
A19: Option B total per scan (GPT-4o + Sonar Pro + DataForSEO) | D19: =D15+D16+D17 -> 0.025
A20: Option B total per scan (cheaper models: GPT-4o-mini + Sonar base + DataForSEO) | D20: =('Vendor Pricing & Assumptions'!$B$17*'Vendor Pricing & Assumptions'!B7+'Vendor Pricing & Assumptions'!$B$18*'Vendor Pricing & Assumptions'!C7)/1000000+'Vendor Pricing & Assumptions'!D7+('Vendor Pricing & Assumptions'!$B$17*'Vendor Pricing & Assumptions'!B9+'Vendor Pricing & Assumptions'!$B$18*'Vendor Pricing & Assumptions'!C9)/1000000+'Vendor Pricing & Assumptions'!D9+D17 -> 0.014635
A22: Summary — cost multiple vs. Option A
A23: Build | B23: Cost per scan | C23: x Option A (Sonnet) | D23: New vendor accounts required
A24: Option A — Sonnet | B24: =D10 -> 0.00675 | C24: =B24/D10 -> 1 | D24: None — Anthropic already in use
A25: Option A — Haiku | B25: =D11 -> 0.00225 | C25: =B25/D10 -> 0.33333333 | D25: None — Anthropic already in use
A26: Option B — higher-quality models | B26: =D19 -> 0.025 | C26: =B26/D10 -> 3.7037037 | D26: OpenAI + Perplexity + DataForSEO (3 new)
A27: Option B — cheaper models | B27: =D20 -> 0.014635 | C27: =B27/D10 -> 2.1681481 | D27: OpenAI + Perplexity + DataForSEO (3 new)

Sheet Monthly Cost vs Plan Revenue
A1: Monthly Cost vs Plan Revenue — new feature stacked on existing AI cost
A3: Part 1 — Existing AI cost per plan (already shipped, not new)
A4: Reconstructs the same worst-case-per-generation math already used and trusted in the Enterprise fair-use fix (pricing review doc, section 8: "a Sonnet generation costs about $0.03"). Cross-check: this model computes $0.0285/generation from 500 input + 1,800 output tokens at Sonnet's $3/$15 rate, matching that published figure.
A6: Existing full-generation token assumption (content tools, NOT the shorter visibility-scan prompt above)
A7: Input tokens per existing generation | B7: 500
A8: Output tokens per existing generation | B8: 1800
A10: Plan | B10: Monthly generation quota | C10: Worst-case model | D10: Cost / generation | E10: Existing monthly AI cost | F10: Plan price
A11: Free | B11: 90 | C11: Haiku (all Free-plan generations forced to Haiku) | D11: =('Vendor Pricing & Assumptions'!B5*$B$7+'Vendor Pricing & Assumptions'!C5*$B$8)/1000000 -> 0.0095 | E11: =B11*D11 -> 0.855 | F11: 0
A12: Pro | B12: 200 | C12: Sonnet (worst case — 9/12 tools are Sonnet-tier) | D12: =('Vendor Pricing & Assumptions'!B4*$B$7+'Vendor Pricing & Assumptions'!C4*$B$8)/1000000 -> 0.0285 | E12: =B12*D12 -> 5.7 | F12: 29
A13: Enterprise | B13: 3000 | C13: Sonnet (worst case, fair-use cap = 3,000/mo) | D13: =('Vendor Pricing & Assumptions'!B4*$B$7+'Vendor Pricing & Assumptions'!C4*$B$8)/1000000 -> 0.0285 | E13: =B13*D13 -> 85.5 | F13: 99
A15: Part 2 — New AI-visibility feature cost, stacked on top (Option A vs B)
A16: Assumed scans/month per plan are PLACEHOLDERS, not decided — this is one of the open items in the scoping doc. Edit the yellow cells to test different quota levels; every total below recalculates.
A18: Plan | B18: Assumed AI-visibility scans / month | C18: Option A cost/mo (Sonnet) | D18: Option B cost/mo (higher-quality) | E18: Existing + Option A total | F18: Existing + Option B total
A19: Free | B19: 0 | C19: =B19*'Cost Per Scan (A vs B)'!$D$10 -> 0 | D19: =B19*'Cost Per Scan (A vs B)'!$D$19 -> 0 | E19: =E11+C19 -> 0.855 | F19: =E11+D19 -> 0.855
A20: Pro | B20: 20 | C20: =B20*'Cost Per Scan (A vs B)'!$D$10 -> 0.135 | D20: =B20*'Cost Per Scan (A vs B)'!$D$19 -> 0.5 | E20: =E12+C20 -> 5.835 | F20: =E12+D20 -> 6.2
A21: Enterprise | B21: 100 | C21: =B21*'Cost Per Scan (A vs B)'!$D$10 -> 0.675 | D21: =B21*'Cost Per Scan (A vs B)'!$D$19 -> 2.5 | E21: =E13+C21 -> 86.175 | F21: =E13+D21 -> 88
A23: Part 3 — Combined AI cost as % of plan revenue
A24: Plan | B24: Plan price | C24: Existing-only, % of revenue | D24: Existing + Option A, % of revenue | E24: Existing + Option B, % of revenue | F24: Reads as
A25: Free | B25: =F11 -> 0 | C25: =IF(F11=0,"n/a (no revenue)",E11/F11) -> n/a (no revenue) | D25: =IF(F11=0,"n/a (no revenue)",E19/F11) -> n/a (no revenue) | E25: =IF(F11=0,"n/a (no revenue)",F19/F11) -> n/a (no revenue)
A26: Pro | B26: =F12 -> 29 | C26: =IF(F12=0,"n/a (no revenue)",E12/F12) -> 0.19655172 | D26: =IF(F12=0,"n/a (no revenue)",E20/F12) -> 0.2012069 | E26: =IF(F12=0,"n/a (no revenue)",F20/F12) -> 0.2137931
A27: Enterprise | B27: =F13 -> 99 | C27: =IF(F13=0,"n/a (no revenue)",E13/F13) -> 0.86363636 | D27: =IF(F13=0,"n/a (no revenue)",E21/F13) -> 0.87045455 | E27: =IF(F13=0,"n/a (no revenue)",F21/F13) -> 0.88888889
A29: Part 4 — Gross profit per user/month if Option A ships (Claude-only simulation)
A30: Gross profit here = plan price minus ALL worst-case AI cost (existing 12-tool generations + the new AI-visibility feature at the scan volumes set in Part 2). Does not include Stripe fees, hosting, or any non-AI cost — this is an AI-cost-only profit view, consistent with the rest of this model.
A32: Plan | B32: Plan price | C32: Total AI cost (existing + Option A) | D32: Gross profit ($) | E32: Gross margin (%) | F32: Profit given up vs. before this feature
A33: Free | B33: =F11 -> 0 | C33: =E19 -> 0.855 | D33: =F11-E19 -> -0.855 | E33: =IF(F11=0,"n/a (no revenue)",(F11-E19)/F11) -> n/a (no revenue) | F33: =E19-E11 -> 0
A34: Pro | B34: =F12 -> 29 | C34: =E20 -> 5.835 | D34: =F12-E20 -> 23.165 | E34: =IF(F12=0,"n/a (no revenue)",(F12-E20)/F12) -> 0.7987931 | F34: =E20-E12 -> 0.135
A35: Enterprise | B35: =F13 -> 99 | C35: =E21 -> 86.175 | D35: =F13-E21 -> 12.825 | E35: =IF(F13=0,"n/a (no revenue)",(F13-E21)/F13) -> 0.12954545 | F35: =E21-E13 -> 0.675
A37: Part 5 — What it takes to hit a target margin (Sri: 75-80%, need room for ad spend)
A38: Edit the yellow target-margin cell. For each plan, at the CURRENT price and CURRENT worst-case cost: whether it already clears the target, and if not, both the price that would clear it at today's fair-use cap, and the fair-use cap that would clear it at today's price — two separate levers, pick one or blend both.
A40: Target gross margin | B40: 0.78
A42: Plan | B42: Current price | C42: Current worst-case cost | D42: Current margin | E42: Meets target? | F42: Price needed to hit target (same cap)
A43: Free | B43: =F11 -> 0 | C43: =E11 -> 0.855 | D43: =IF(F11=0,"n/a",(F11-E11)/F11) -> n/a | E43: =IF(F11=0,"n/a",IF((F11-E11)/F11>=$B$40,"YES","NO")) -> n/a | F43: =IF(F11=0,"n/a",E11/(1-$B$40)) -> n/a
A44: Pro | B44: =F12 -> 29 | C44: =E12 -> 5.7 | D44: =IF(F12=0,"n/a",(F12-E12)/F12) -> 0.80344828 | E44: =IF(F12=0,"n/a",IF((F12-E12)/F12>=$B$40,"YES","NO")) -> YES | F44: =IF(F12=0,"n/a",E12/(1-$B$40)) -> 25.909091
A45: Enterprise | B45: =F13 -> 99 | C45: =E13 -> 85.5 | D45: =IF(F13=0,"n/a",(F13-E13)/F13) -> 0.13636364 | E45: =IF(F13=0,"n/a",IF((F13-E13)/F13>=$B$40,"YES","NO")) -> NO | F45: =IF(F13=0,"n/a",E13/(1-$B$40)) -> 388.63636
A47: Plan | B47: Current fair-use cap (gens/mo) | C47: Cost / generation | D47: Max cap to hit target (same price) | E47: Cap cut needed
A48: Free | B48: =B11 -> 90 | C48: =D11 -> 0.0095 | D48: =IF(F11=0,"n/a",(F11*(1-$B$40))/D11) -> n/a | E48: =IF(F11=0,"n/a",B11-(F11*(1-$B$40))/D11) -> n/a
A49: Pro | B49: =B12 -> 200 | C49: =D12 -> 0.0285 | D49: =IF(F12=0,"n/a",(F12*(1-$B$40))/D12) -> 223.85965 | E49: =IF(F12=0,"n/a",B12-(F12*(1-$B$40))/D12) -> -23.859649
A50: Enterprise | B50: =B13 -> 3000 | C50: =D13 -> 0.0285 | D50: =IF(F13=0,"n/a",(F13*(1-$B$40))/D13) -> 764.21053 | E50: =IF(F13=0,"n/a",B13-(F13*(1-$B$40))/D13) -> 2235.7895
